README.rst
pyproject.toml
setup.py
bin/objd
objd/__init__.py
objd/broker.py
objd/cli.py
objd/commands.py
objd/config.py
objd/console.py
objd/decoder.py
objd/default.py
objd/encoder.py
objd/errors.py
objd/event.py
objd/handler.py
objd/help.py
objd/iface.py
objd/locks.py
objd/log.py
objd/main.py
objd/object.py
objd/parse.py
objd/persist.py
objd/repeater.py
objd/run.py
objd/thread.py
objd/timer.py
objd/utils.py
objd.egg-info/PKG-INFO
objd.egg-info/SOURCES.txt
objd.egg-info/dependency_links.txt
objd.egg-info/top_level.txt
objd.egg-info/zip-safe
objd/modules/__init__.py
objd/modules/cmd.py
objd/modules/err.py
objd/modules/fnd.py
objd/modules/irc.py
objd/modules/log.py
objd/modules/mod.py
objd/modules/opm.py
objd/modules/rss.py
objd/modules/tdo.py
objd/modules/thr.py
objd/modules/tmr.py
objd/modules/upt.py
objd/modules/ver.py
objd/user/__init__.py