Metadata-Version: 2.1
Name: objd
Version: 20
Summary: objects daemon
Author-email: xobjectz <objx@proton.me>
License: Public Domain
Project-URL: home, https://pypi.org/project/objd
Project-URL: bugs, https://github.com/xobjectz/objd/issues
Project-URL: source, https://github.com/xobjectz/objd
Classifier: Development Status :: 3 - Alpha
Classifier: License :: Public Domain
Classifier: Operating System :: Unix
Classifier: Programming Language :: Python
Classifier: Topic :: Utilities
